<?xml version="1.0" encoding="utf-8" ?>
<dwsync>
<file name="admin-functions.php" server="192.168.1.214" local="131237038425726195" remote="131238973800000000" Dst="1" />
<file name="class-contact-forms-list-table.php" server="192.168.1.214" local="131237038426127452" remote="131238973800000000" Dst="1" />
<file name="editor.php" server="192.168.1.214" local="131237038428170860" remote="131238973800000000" Dst="1" />
<file name="help-tabs.php" server="192.168.1.214" local="131237038428822664" remote="131238973800000000" Dst="1" />
<file name="meta-boxes.php" server="192.168.1.214" local="131237038430354034" remote="131238973800000000" Dst="1" />
<file name="tag-generator.php" server="192.168.1.214" local="131237038430674882" remote="131238973800000000" Dst="1" />
<file name="admin-functions.php" server="192.168.1.204" local="131237038425726195" remote="131288430600000000" Dst="1" />
<file name="class-contact-forms-list-table.php" server="192.168.1.204" local="131237038426127452" remote="131288430600000000" Dst="1" />
<file name="editor.php" server="192.168.1.204" local="131237038428170860" remote="131288430600000000" Dst="1" />
<file name="help-tabs.php" server="192.168.1.204" local="131237038428822664" remote="131288430600000000" Dst="1" />
<file name="meta-boxes.php" server="192.168.1.204" local="131237038430354034" remote="131288430600000000" Dst="1" />
<file name="tag-generator.php" server="192.168.1.204" local="131237038430674882" remote="131288430600000000" Dst="1" />
<file name="admin-functions.php" server="192.168.1.28" local="131667254614947839" remote="131667159600000000" Dst="2" />
<file name="class-contact-forms-list-table.php" server="192.168.1.28" local="131667254615571839" remote="131667159600000000" Dst="2" />
<file name="editor.php" server="192.168.1.28" local="131667254616351839" remote="131667159600000000" Dst="2" />
<file name="help-tabs.php" server="192.168.1.28" local="131667254616819839" remote="131667159600000000" Dst="2" />
<file name="meta-boxes.php" server="192.168.1.28" local="131237038430354034" remote="131667154800000000" Dst="2" />
<file name="tag-generator.php" server="192.168.1.28" local="131667254617599839" remote="131667159600000000" Dst="2" />
<file name="welcome-panel.php" server="192.168.1.28" local="131667254618067839" remote="131667159600000000" Dst="2" />
</dwsync>